{"name":"build-javascript","namedChunkGroups":{"polyfill":{"name":"polyfill","assets":[{"name":"webpack-runtime-706ed34a5e187b38aa2e.js","size":3851},{"name":"polyfill-e38e49499841dee94037.js","size":85838}],"filteredAssets":0,"assetsSize":89689,"filteredAuxiliaryAssets":2,"auxiliaryAssetsSize":223490},"app":{"name":"app","assets":[{"name":"webpack-runtime-706ed34a5e187b38aa2e.js","size":3851},{"name":"framework-e21629b72f495dbefe32.js","size":140542},{"name":"app-5e3af9f7f704e79dd52d.js","size":93742}],"filteredAssets":0,"assetsSize":238135,"filteredAuxiliaryAssets":3,"auxiliaryAssetsSize":793956},"component---src-pages-404-tsx":{"name":"component---src-pages-404-tsx","assets":[{"name":"component---src-pages-404-tsx-1005278e7555252e7bae.js","size":891}],"filteredAssets":0,"assetsSize":891,"filteredAuxiliaryAssets":1,"auxiliaryAssetsSize":1981},"component---src-pages-index-tsx":{"name":"component---src-pages-index-tsx","assets":[{"name":"component---src-pages-index-tsx-3a64c22ee1c2ce62d2b5.js","size":1065}],"filteredAssets":0,"assetsSize":1065,"filteredAuxiliaryAssets":1,"auxiliaryAssetsSize":2969},"component---src-pages-news-tsx":{"name":"component---src-pages-news-tsx","assets":[{"name":"component---src-pages-news-tsx-04a7b9afbbbc57b93af0.js","size":954}],"filteredAssets":0,"assetsSize":954,"filteredAuxiliaryAssets":1,"auxiliaryAssetsSize":2700},"component---src-templates-news-post-tsx":{"name":"component---src-templates-news-post-tsx","assets":[{"name":"component---src-templates-news-post-tsx-6e5bb1ae086833ac6c0f.js","size":21141}],"filteredAssets":0,"assetsSize":21141,"filteredAuxiliaryAssets":1,"auxiliaryAssetsSize":84022}},"assetsByChunkName":{"polyfill":["webpack-runtime-706ed34a5e187b38aa2e.js","polyfill-e38e49499841dee94037.js"],"app":["webpack-runtime-706ed34a5e187b38aa2e.js","framework-e21629b72f495dbefe32.js","app-5e3af9f7f704e79dd52d.js"],"component---src-pages-404-tsx":["component---src-pages-404-tsx-1005278e7555252e7bae.js"],"component---src-pages-index-tsx":["component---src-pages-index-tsx-3a64c22ee1c2ce62d2b5.js"],"component---src-pages-news-tsx":["component---src-pages-news-tsx-04a7b9afbbbc57b93af0.js"],"component---src-templates-news-post-tsx":["component---src-templates-news-post-tsx-6e5bb1ae086833ac6c0f.js"]},"childAssetsByChunkName":{}}